{
  "metadata": {
    "masechet": "megillah",
    "masechet_he": "מגילה",
    "daf": "8a",
    "source": [
      "rashi_girsa"
    ],
    "schema_version": 1,
    "generated_by": "tzurat/rashi_recension/",
    "counts": {
      "segments_changed": 2,
      "changes": 2,
      "applied": 0,
      "by_type": {
        "orthographic": 2
      },
      "by_confidence": {
        "low": 2
      },
      "by_source": {
        "rashi_girsa": 2
      },
      "skipped_abbrev": 0
    }
  },
  "segments": [
    {
      "segment_id": 16,
      "original_text": "״וְכִי יִטְהַר הַזָּב מִזּוֹבוֹ״ מַאי דָּרְשַׁתְּ בֵּיהּ? הַהוּא מִיבְּעֵי לֵיהּ לְכִדְתַנְיָא: ״וְכִי יִטְהַר הַזָּב״ — לִכְשֶׁיִּפְסוֹק מִזּוֹבוֹ, [״מִזּוֹבוֹ״ —] וְלֹא מִזּוֹבוֹ וְנִגְעוֹ. ״מִזּוֹבוֹ וְסָפַר״ — לִימֵּד עַל זָב בַּעַל שְׁתֵּי רְאִיּוֹת שֶׁטָּעוּן",
      "reconstructed_text": "״וְכִי יִטְהַר הַזָּב מִזּוֹבוֹ״ מַאי דָּרְשַׁתְּ בֵּיהּ? הַהוּא מִיבְּעֵי לֵיהּ לְכִדְתַנְיָא: ״וְכִי יִטְהַר הַזָּב״ — לִכְשֶׁיִּפְסוֹק מִזּוֹבוֹ, [״מִזּוֹבוֹ״ —] וְלֹא מִזּוֹבוֹ וְנִגְעוֹ. ״מִזּוֹבוֹ וְסָפַר״ — לִימֵּד עַל זָב בַּעַל שְׁתֵּי רְאִיּוֹת שֶׁטָּעוּן",
      "reconstructed_html": "״וְכִי יִטְהַר הַזָּב מִזּוֹבוֹ״ מַאי דָּרְשַׁתְּ בֵּיהּ? הַהוּא מִיבְּעֵי לֵיהּ לְכִדְתַנְיָא: ״וְכִי יִטְהַר הַזָּב״ — לִכְשֶׁיִּפְסוֹק מִזּוֹבוֹ, [״מִזּוֹבוֹ״ —] וְלֹא מִזּוֹבוֹ וְנִגְעוֹ. ״מִזּוֹבוֹ וְסָפַר״ — לִימֵּד עַל זָב בַּעַל שְׁתֵּי רְאִיּוֹת שֶׁטָּעוּן",
      "changes": [
        {
          "type": "orthographic",
          "confidence": "low",
          "apply": false,
          "source": "rashi_girsa",
          "source_ref": "Rashi on Megillah 8a:17:1",
          "marker": "הכי גרסינן",
          "marker_type": "assert",
          "seg_token_index": 21,
          "original": "וְנִגְעוֹ.",
          "proposed": "ומנגעו",
          "proposed_vocalized": false,
          "before_context": "וְלֹא מִזּוֹבוֹ",
          "after_context": "״מִזּוֹבוֹ וְסָפַר״"
        }
      ]
    },
    {
      "segment_id": 17,
      "original_text": "סְפִירַת שִׁבְעָה. וַהֲלֹא דִּין הוּא, אִם מְטַמֵּא מִשְׁכָּב וּמוֹשָׁב לֹא יְהֵא טָעוּן סְפִירַת שִׁבְעָה?",
      "reconstructed_text": "סְפִירַת שִׁבְעָה. וַהֲלֹא דִּין הוּא, אִם מְטַמֵּא מִשְׁכָּב וּמוֹשָׁב לֹא יְהֵא טָעוּן סְפִירַת שִׁבְעָה?",
      "reconstructed_html": "סְפִירַת שִׁבְעָה. וַהֲלֹא דִּין הוּא, אִם מְטַמֵּא מִשְׁכָּב וּמוֹשָׁב לֹא יְהֵא טָעוּן סְפִירַת שִׁבְעָה?",
      "changes": [
        {
          "type": "orthographic",
          "confidence": "low",
          "apply": false,
          "source": "rashi_girsa",
          "source_ref": "Rashi on Megillah 8a:18:1",
          "marker": "ה\"ג",
          "marker_type": "assert",
          "seg_token_index": 2,
          "original": "וַהֲלֹא",
          "proposed": "הלא",
          "proposed_vocalized": false,
          "before_context": "סְפִירַת שִׁבְעָה.",
          "after_context": "דִּין הוּא,"
        }
      ]
    }
  ]
}