{
  "metadata": {
    "masechet": "niddah",
    "masechet_he": "נדה",
    "daf": "34b",
    "source": [
      "rashi_girsa"
    ],
    "schema_version": 1,
    "generated_by": "tzurat/rashi_recension/",
    "counts": {
      "segments_changed": 1,
      "changes": 3,
      "applied": 3,
      "by_type": {
        "prefix": 1,
        "deletion": 2
      },
      "by_confidence": {
        "medium": 3
      },
      "by_source": {
        "rashi_girsa": 3
      },
      "skipped_abbrev": 1
    }
  },
  "segments": [
    {
      "segment_id": 12,
      "original_text": "וְאִיבָּעֵית אֵימָא, אָמְרִי לָךְ בֵּית שַׁמַּאי: הַאי ״לְזָכָר״ מִיבְּעֵי לֵיהּ, ״לְזָכָר״ — כֹּל שֶׁהוּא זָכָר, (הַאי), בֵּין גָּדוֹל בֵּין קָטָן. וּבֵית הִלֵּל, נָפְקָא",
      "reconstructed_text": "בָּעֵית אֵימָא, אָמְרִי לָךְ בֵּית שַׁמַּאי: הַאי ״לְזָכָר״ מִיבְּעֵי לֵיהּ, ״לְזָכָר״ — זָכָר, (הַאי), בֵּין גָּדוֹל בֵּין קָטָן. וּבֵית הִלֵּל, נָפְקָא",
      "reconstructed_html": "<span class=\"girsa-change\" data-change-type=\"prefix\" data-confidence=\"medium\" data-source=\"rashi_girsa\" data-source-ref=\"Rashi on Niddah 34b:12:1\" data-marker=\"ה&quot;ג\" data-original=\"וְאִיבָּעֵית\"><span class=\"girsa-letter-del\">וְ</span><span class=\"girsa-letter-del\">אִ</span><span class=\"girsa-letter-del\">י</span>בָּעֵית</span> אֵימָא, אָמְרִי לָךְ בֵּית שַׁמַּאי: הַאי ״לְזָכָר״ מִיבְּעֵי לֵיהּ, ״לְזָכָר״ — <span class=\"girsa-change girsa-deletion\" data-change-type=\"deletion\" data-confidence=\"medium\" data-source=\"rashi_girsa\" data-source-ref=\"Rashi on Niddah 34b:13:1\" data-marker=\"ל&quot;ג\" data-original=\"כֹּל\">כֹּל</span> <span class=\"girsa-change girsa-deletion\" data-change-type=\"deletion\" data-confidence=\"medium\" data-source=\"rashi_girsa\" data-source-ref=\"Rashi on Niddah 34b:13:1\" data-marker=\"ל&quot;ג\" data-original=\"שֶׁהוּא\">שֶׁהוּא</span> זָכָר, (הַאי), בֵּין גָּדוֹל בֵּין קָטָן. וּבֵית הִלֵּל, נָפְקָא",
      "changes": [
        {
          "type": "prefix",
          "confidence": "medium",
          "apply": true,
          "source": "rashi_girsa",
          "source_ref": "Rashi on Niddah 34b:12:1",
          "marker": "ה\"ג",
          "marker_type": "assert",
          "seg_token_index": 0,
          "original": "וְאִיבָּעֵית",
          "proposed": "בעית",
          "recon_text": "בָּעֵית",
          "marked_html": "<span class=\"girsa-letter-del\">וְ</span><span class=\"girsa-letter-del\">אִ</span><span class=\"girsa-letter-del\">י</span>בָּעֵית",
          "proposed_vocalized": false,
          "before_context": "",
          "after_context": "אֵימָא, אָמְרִי"
        },
        {
          "type": "deletion",
          "confidence": "medium",
          "apply": true,
          "source": "rashi_girsa",
          "source_ref": "Rashi on Niddah 34b:13:1",
          "marker": "ל\"ג",
          "marker_type": "delete",
          "seg_token_index": 12,
          "original": "כֹּל",
          "proposed": "",
          "before_context": "״לְזָכָר״ —",
          "after_context": "שֶׁהוּא זָכָר,"
        },
        {
          "type": "deletion",
          "confidence": "medium",
          "apply": true,
          "source": "rashi_girsa",
          "source_ref": "Rashi on Niddah 34b:13:1",
          "marker": "ל\"ג",
          "marker_type": "delete",
          "seg_token_index": 13,
          "original": "שֶׁהוּא",
          "proposed": "",
          "before_context": "— כֹּל",
          "after_context": "זָכָר, (הַאי),"
        }
      ]
    }
  ]
}