{
  "metadata": {
    "masechet": "sukkah",
    "masechet_he": "סוכה",
    "daf": "34a",
    "source": [
      "rashi_girsa",
      "rashi_dh"
    ],
    "schema_version": 1,
    "generated_by": "tzurat/rashi_recension/",
    "counts": {
      "segments_changed": 2,
      "changes": 2,
      "applied": 1,
      "by_type": {
        "girsa-confirmed": 1,
        "wordbreak": 1
      },
      "by_confidence": {
        "low": 2
      },
      "by_source": {
        "rashi_girsa": 1,
        "rashi_dh": 1
      },
      "skipped_abbrev": 0
    }
  },
  "segments": [
    {
      "segment_id": 0,
      "original_text": "אַבָּא שָׁאוּל אוֹמֵר: ״עַרְבֵי״ — שְׁתַּיִם. אַחַת לַלּוּלָב,",
      "reconstructed_text": "אַבָּא שָׁאוּל אוֹמֵר: ״עַרְבֵי״ — שְׁתַּיִם. אַחַת לַלּוּלָב,",
      "reconstructed_html": "אַבָּא שָׁאוּל אוֹמֵר: ״עַרְבֵי״ — שְׁתַּיִם. אַחַת לַלּוּלָב,",
      "changes": [
        {
          "type": "girsa-confirmed",
          "confidence": "low",
          "apply": false,
          "source": "rashi_girsa",
          "source_ref": "Rashi on Sukkah 34a:4:1",
          "marker": "לא גרסינן",
          "marker_type": "delete",
          "rashi_excerpt": "גרסינן ולא גרסינן אלא ולאו לפרושי טעמא דמתני' אלא מלתא באפי נפשה היא הואיל ואיירי בקרא פרשיה",
          "confirmed_status": "delete-partial",
          "target_phrase": "אלא ולאו לפרושי טעמא דמתני' אלא",
          "seg_token_index": 0,
          "original": "",
          "proposed": "",
          "before_context": "",
          "after_context": "שָׁאוּל אוֹמֵר:"
        }
      ]
    },
    {
      "segment_id": 5,
      "original_text": "עֲרָבָה, וְהֵן שָׂמוּ עַצְמָן כְּצַפְצָפָה שֶׁבֶּהָרִים.  תָּנוּ רַבָּנַן: אֵי זֶהוּ עֲרָבָה וְאֵיזֶהוּ צַפְצָפָה? עֲרָבָה, קָנֶה שֶׁלָּהּ אָדוֹם, וְעָלֶה שֶׁלָּהּ מָשׁוּךְ וּפִיהָ חָלָק. צַפְצָפָה, קָנֶה שֶׁלָּהּ לָבָן, וְעָלֶה שֶׁלָּהּ עָגוֹל וּפִיהָ דּוֹמֶה לְמַגָּל. וְהָא תַּנְיָא: דּוֹמֶה לְמַגָּל כָּשֵׁר, דּוֹמֶה לְמַסָּר — פָּסוּל! אֲמַר אַבָּיֵי: כִּי תַּנְיָא הָהִיא,",
      "reconstructed_text": "עֲרָבָה, וְהֵן שָׂמוּ עַצְמָן כְּצַפְצָפָה שֶׁבֶּהָרִים. תָּנוּ רַבָּנַן: אֵי זֶהוּ עֲרָבָה וְאֵיזֶהוּ צַפְצָפָה? עֲרָבָה, קָנֶה שֶׁלָּהּ אָדוֹם, וְעָלֶה שֶׁלָּהּ מָשׁוּךְ וּפִיהָ חָלָק. צַפְצָפָה, קָנֶה שֶׁלָּהּ לָבָן, וְעָלֶה שֶׁלָּהּ עָגוֹל וּפִיהָ דּוֹמֶה לְמַגָּל. והתניא דּוֹמֶה לְמַגָּל כָּשֵׁר, דּוֹמֶה לְמַסָּר — פָּסוּל! אֲמַר אַבָּיֵי: כִּי תַּנְיָא הָהִיא,",
      "reconstructed_html": "עֲרָבָה, וְהֵן שָׂמוּ עַצְמָן כְּצַפְצָפָה שֶׁבֶּהָרִים. תָּנוּ רַבָּנַן: אֵי זֶהוּ עֲרָבָה וְאֵיזֶהוּ צַפְצָפָה? עֲרָבָה, קָנֶה שֶׁלָּהּ אָדוֹם, וְעָלֶה שֶׁלָּהּ מָשׁוּךְ וּפִיהָ חָלָק. צַפְצָפָה, קָנֶה שֶׁלָּהּ לָבָן, וְעָלֶה שֶׁלָּהּ עָגוֹל וּפִיהָ דּוֹמֶה לְמַגָּל. <span class=\"girsa-change girsa-dh\" data-change-type=\"wordbreak\" data-confidence=\"low\" data-source=\"rashi_dh\" data-source-ref=\"Rashi on Sukkah 34a:6:3\" data-marker=\"(dibbur hamatchil)\" data-original=\"וְהָא תַּנְיָא:\">והתניא</span> דּוֹמֶה לְמַגָּל כָּשֵׁר, דּוֹמֶה לְמַסָּר — פָּסוּל! אֲמַר אַבָּיֵי: כִּי תַּנְיָא הָהִיא,",
      "changes": [
        {
          "type": "wordbreak",
          "confidence": "low",
          "apply": true,
          "source": "rashi_dh",
          "source_ref": "Rashi on Sukkah 34a:6:3",
          "marker": "(dibbur hamatchil)",
          "marker_type": "dh",
          "seg_token_index": 32,
          "original": "וְהָא תַּנְיָא:",
          "proposed": "והתניא",
          "recon_text": "והתניא",
          "marked_html": null,
          "merge_indices": [
            32,
            33
          ],
          "before_context": "דּוֹמֶה לְמַגָּל.",
          "after_context": "דּוֹמֶה לְמַגָּל"
        }
      ]
    }
  ]
}