{
  "masechet_slug": "berakhot",
  "masechet_title": "Berakhot",
  "daf": "8a",
  "display_name_he": "תּוֹרָה אוֹר הֶחָדָשׁ",
  "references": [
    {
      "ref": "Psalms 69:14",
      "he_ref": "תהילים ס״ט:י״ד",
      "url": "https://www.sefaria.org/Psalms_69%3A14?lang=bi",
      "segment_ids": [
        0
      ],
      "anchor_refs": [
        "Berakhot 8a:1"
      ],
      "hebrew": "וַאֲנִ֤י תְפִלָּֽתִי־לְךָ֨&thinsp;<b>׀</b> יְהֹוָ֡ה עֵ֤ת רָצ֗וֹן אֱלֹהִ֥ים בְּרׇב־חַסְדֶּ֑ךָ עֲ֝נֵ֗נִי בֶּאֱמֶ֥ת יִשְׁעֶֽךָ׃",
      "english": "<span class=\"poetry indentAll\">As for me, may my prayer come to You, O E<small>TERNAL</small> One,</span><br><span class=\"poetry indentAllDouble\">at a favorable moment;</span><br><span class=\"poetry indentAllDouble\">O God, in Your abundant faithfulness,</span><br><span class=\"poetry indentAllDouble\">answer me with Your sure deliverance.</span>",
      "marker_line_index": 0,
      "placement_method": "quote_match",
      "placement_score": 8,
      "matched_snippet": "ואני תפלתי לך ה עת רצון",
      "source_kind": "direct_quote"
    },
    {
      "ref": "Proverbs 18:22",
      "he_ref": "משלי י״ח:כ״ב",
      "url": "https://www.sefaria.org/Proverbs_18%3A22?lang=bi",
      "segment_ids": [
        9
      ],
      "anchor_refs": [
        "Berakhot 8a:10"
      ],
      "hebrew": "מָצָ֣א אִ֭שָּׁה מָ֣צָא ט֑וֹב וַיָּ֥פֶק רָ֝צ֗וֹן מֵיְהֹוָֽה׃",
      "english": "<span class=\"poetry indentAll\">He who finds a wife has found happiness</span><br><span class=\"poetry indentAll\">And has won G<small>OD</small>’s favor.</span>",
      "marker_line_index": 24,
      "placement_method": "quote_match",
      "placement_score": 4,
      "matched_snippet": "מצא",
      "source_kind": "direct_quote"
    },
    {
      "ref": "Proverbs 8:35",
      "he_ref": "משלי ח׳:ל״ה",
      "url": "https://www.sefaria.org/Proverbs_8%3A35?lang=bi",
      "segment_ids": [
        10
      ],
      "anchor_refs": [
        "Berakhot 8a:11"
      ],
      "hebrew": "כִּ֣י מֹ֭צְאִי <span class=\"mam-kq\"><span class=\"mam-kq-k\">(מצאי)</span> <span class=\"mam-kq-q\">[מָצָ֣א]</span></span> חַיִּ֑ים וַיָּ֥פֶק רָ֝צ֗וֹן מֵיְהֹוָֽה׃",
      "english": "<span class=\"poetry indentAll\">For one who finds me finds life</span><br><span class=\"poetry indentAll\">And obtains favor from G<small>OD</small>.</span>",
      "marker_line_index": 26,
      "placement_method": "quote_match",
      "placement_score": 23,
      "matched_snippet": "כי מצאי מצא חיים",
      "source_kind": "direct_quote"
    },
    {
      "ref": "Job 3:22",
      "he_ref": "איוב ג׳:כ״ב",
      "url": "https://www.sefaria.org/Job_3%3A22?lang=bi",
      "segment_ids": [
        13
      ],
      "anchor_refs": [
        "Berakhot 8a:14"
      ],
      "hebrew": "הַשְּׂמֵחִ֥ים אֱלֵי־גִ֑יל יָ֝שִׂ֗ישׂוּ כִּ֣י יִמְצְאוּ־קָֽבֶר׃",
      "english": "<span class=\"poetry indentAll\">Who rejoice to exultation,</span><br><span class=\"poetry indentAll\">And are glad to reach the grave;</span>",
      "marker_line_index": 32,
      "placement_method": "quote_match",
      "placement_score": 8,
      "matched_snippet": "השמחים אלי גיל ישישו כי ימצאו קבר",
      "source_kind": "direct_quote"
    },
    {
      "ref": "Psalms 87:2",
      "he_ref": "תהילים פ״ז:ב׳",
      "url": "https://www.sefaria.org/Psalms_87%3A2?lang=bi",
      "segment_ids": [
        16
      ],
      "anchor_refs": [
        "Berakhot 8a:17"
      ],
      "hebrew": "אֹהֵ֣ב יְ֭הֹוָה שַׁעֲרֵ֣י צִיּ֑וֹן מִ֝כֹּ֗ל מִשְׁכְּנ֥וֹת יַעֲקֹֽב׃",
      "english": "<span class=\"poetry indentAllDouble\">the gates of Zion—</span><br><span class=\"poetry indentAllDouble\">G<small>OD</small> loves</span><br><span class=\"poetry indentAllDouble\">more than all the dwellings of Jacob.</span>",
      "marker_line_index": 37,
      "placement_method": "quote_match",
      "placement_score": 41,
      "matched_snippet": "אהב ה שערי ציון מכל משכנות יעקב",
      "source_kind": "direct_quote"
    },
    {
      "ref": "Job 36:5",
      "he_ref": "איוב ל״ו:ה׳",
      "url": "https://www.sefaria.org/Job_36%3A5?lang=bi",
      "segment_ids": [
        2
      ],
      "anchor_refs": [
        "Berakhot 8a:3"
      ],
      "hebrew": "הֶן־אֵ֣ל כַּ֭בִּיר וְלֹ֣א יִמְאָ֑ס כַּ֝בִּ֗יר כֹּ֣חַֽ לֵֽב׃",
      "english": "<span class=\"poetry indentAll\">See, God is mighty, but not contemptuous—</span><br><span class=\"poetry indentAll\">Mighty in strength and mind—</span>",
      "marker_line_index": 4,
      "placement_method": "quote_match",
      "placement_score": 19,
      "matched_snippet": "הן אל כביר ולא ימאס",
      "source_kind": "direct_quote"
    },
    {
      "ref": "Deuteronomy 11:21",
      "he_ref": "דברים י״א:כ״א",
      "url": "https://www.sefaria.org/Deuteronomy_11%3A21?lang=bi",
      "segment_ids": [
        5
      ],
      "anchor_refs": [
        "Berakhot 8a:6"
      ],
      "hebrew": "לְמַ֨עַן יִרְבּ֤וּ יְמֵיכֶם֙ וִימֵ֣י בְנֵיכֶ֔ם עַ֚ל הָֽאֲדָמָ֔ה אֲשֶׁ֨ר נִשְׁבַּ֧ע יְהֹוָ֛ה לַאֲבֹתֵיכֶ֖ם לָתֵ֣ת לָהֶ֑ם כִּימֵ֥י הַשָּׁמַ֖יִם עַל־הָאָֽרֶץ<sup class=\"footnote-marker\">*</sup><i class=\"footnote\">(בספרי תימן הָאָֽרֶ<big>ץ</big> בצד״י גדולה)</i>׃&nbsp;<span class=\"mam-spi-samekh\">{ס}</span>&nbsp;&nbsp;&nbsp;&nbsp;&nbsp;&nbsp;&nbsp;&nbsp;",
      "english": "to the end that you and your children may endure, in the land that G<small>OD</small> swore to your fathers<sup class=\"footnote-marker\">i</sup><i class=\"footnote\"><b>fathers </b>See note at <a class=\"refLink\" data-ref=\"Deuteronomy 1:35\" href=\"Deuteronomy.1.35\">1.35</a>.</i> to assign to them, as long as there is a heaven over the earth.",
      "marker_line_index": 16,
      "placement_method": "quote_match",
      "placement_score": 62,
      "matched_snippet": "למען ירבו ימיכם וימי בניכם על האדמה",
      "source_kind": "direct_quote"
    }
  ],
  "commentary_links": [
    {
      "ref": "Ecclesiastes 7:26",
      "he_ref": "קהלת ז׳:כ״ו",
      "url": "https://www.sefaria.org/Ecclesiastes_7%3A26?lang=bi",
      "segment_ids": [
        9
      ],
      "anchor_refs": [
        "Berakhot 8a:10"
      ],
      "hebrew": "וּמוֹצֶ֨א אֲנִ֜י מַ֣ר מִמָּ֗וֶת אֶת־הָֽאִשָּׁה֙ אֲשֶׁר־הִ֨יא מְצוֹדִ֧ים וַחֲרָמִ֛ים לִבָּ֖הּ אֲסוּרִ֣ים יָדֶ֑יהָ ט֞וֹב לִפְנֵ֤י הָאֱלֹהִים֙ יִמָּלֵ֣ט מִמֶּ֔נָּה וְחוֹטֵ֖א יִלָּ֥כֶד בָּֽהּ׃",
      "english": "Now, I find more bitter than death the woman who is all traps, whose hands are fetters, and whose heart<sup class=\"footnote-marker\">q</sup><i class=\"footnote\"><b>I find more bitter than death the woman who…whose hands…whose heart </b>Or “I find woman more bitter than death; she…her hands…her heart.” Force of Heb. uncertain.</i> is snares. He who is pleasing to God escapes her, and he who is displeasing is caught by her.",
      "marker_line_index": 25,
      "placement_method": "quote_match",
      "placement_score": 30,
      "matched_snippet": "אשה מצא טוב ויפק רצון מה מוצא דכתיב ומוצא אני מר ממות את האשה",
      "source_kind": "commentary_link"
    },
    {
      "ref": "Psalms 68:21",
      "he_ref": "תהילים ס״ח:כ״א",
      "url": "https://www.sefaria.org/Psalms_68%3A21?lang=bi",
      "segment_ids": [
        11,
        12
      ],
      "anchor_refs": [
        "Berakhot 8a:12",
        "Berakhot 8a:13"
      ],
      "hebrew": "הָ֤אֵ֣ל&thinsp;<small>׀</small>&thinsp;לָנוּ֮ אֵ֤ל לְֽמ֫וֹשָׁע֥וֹת וְלֵיהֹוִ֥ה אֲדֹנָ֑י לַ֝מָּ֗וֶת תֹּצָאֽוֹת׃",
      "english": "<span class=\"poetry indentAll\">God is for us a God of deliverance;</span><br><span class=\"poetry indentAllDouble\"> G<small>OD</small> my Sovereign provides an escape from death.</span>",
      "marker_line_index": 26,
      "placement_method": "fallback_anchor_start",
      "placement_score": 2,
      "matched_snippet": "",
      "source_kind": "commentary_link"
    },
    {
      "ref": "II Kings 10:27",
      "he_ref": "מלכים ב י׳:כ״ז",
      "url": "https://www.sefaria.org/II_Kings_10%3A27?lang=bi",
      "segment_ids": [
        14
      ],
      "anchor_refs": [
        "Berakhot 8a:15"
      ],
      "hebrew": "וַֽיִּתְּצ֔וּ אֵ֖ת מַצְּבַ֣ת הַבָּ֑עַל וַֽיִּתְּצוּ֙ אֶת־בֵּ֣ית הַבַּ֔עַל וַיְשִׂמֻ֥הוּ <span class=\"mam-kq\"><span class=\"mam-kq-k\">(למחראות)</span> <span class=\"mam-kq-q\">[לְמֽוֹצָא֖וֹת]</span></span> עַד־הַיּֽוֹם׃",
      "english": "They destroyed the pillar<sup class=\"footnote-marker\">h</sup><i class=\"footnote\"><b>pillar </b>Emendation yields “altar.”</i> of Baal, and they tore down the temple of Baal and turned it into latrines, as is still the case.",
      "marker_line_index": 33,
      "placement_method": "fallback_anchor_start",
      "placement_score": 2,
      "matched_snippet": "",
      "source_kind": "commentary_link"
    },
    {
      "ref": "Isaiah 49:8",
      "he_ref": "ישעיהו מ״ט:ח׳",
      "url": "https://www.sefaria.org/Isaiah_49%3A8?lang=bi",
      "segment_ids": [
        1
      ],
      "anchor_refs": [
        "Berakhot 8a:2"
      ],
      "hebrew": "כֹּ֣ה&thinsp;<b>׀</b> אָמַ֣ר יְהֹוָ֗ה בְּעֵ֤ת רָצוֹן֙ עֲנִיתִ֔יךָ וּבְי֥וֹם יְשׁוּעָ֖ה עֲזַרְתִּ֑יךָ וְאֶצׇּרְךָ֗ וְאֶתֶּנְךָ֙ לִבְרִ֣ית עָ֔ם לְהָקִ֣ים אֶ֔רֶץ לְהַנְחִ֖יל נְחָל֥וֹת שֹׁמֵמֽוֹת׃",
      "english": "<span class=\"poetry indentAll\">Thus said </span> G<small>OD</small>:<br><span class=\"poetry indentAll\">In an hour of favor I answer you,</span><br><span class=\"poetry indentAll\">And on a day of salvation I help you—</span><br><span class=\"poetry indentAll\">I created you and appointed you a covenant people</span><sup class=\"footnote-marker\">d</sup><i class=\"footnote\"><b>a covenant people </b>See the first note at 42.6.</i>—<br><span class=\"poetry indentAll\">Restoring the land,</span><br><span class=\"poetry indentAll\">Allotting anew the desolate holdings,</span>",
      "marker_line_index": 3,
      "placement_method": "quote_match",
      "placement_score": 17,
      "matched_snippet": "בעת רצון עניתיך &star רבי אחא ברבי חנינא אמר",
      "source_kind": "commentary_link"
    },
    {
      "ref": "Psalms 112:1",
      "he_ref": "תהילים קי״ב:א׳",
      "url": "https://www.sefaria.org/Psalms_112%3A1?lang=bi",
      "segment_ids": [
        20
      ],
      "anchor_refs": [
        "Berakhot 8a:21"
      ],
      "hebrew": "הַ֥לְלוּ<span class=\"mam-implicit-maqaf\">־</span>יָ֨הּ&thinsp;<b>׀</b> אַשְׁרֵי־אִ֭ישׁ יָרֵ֣א אֶת־יְהֹוָ֑ה בְּ֝מִצְוֺתָ֗יו חָפֵ֥ץ מְאֹֽד׃",
      "english": "<span class=\"poetry indentAll\">Hallelujah.</span><br><span class=\"poetry indentAll\"> <b>א</b> Happy are those who fear G<small>OD</small>,</span><br><span class=\"poetry indentAllDouble\">who are ardently devoted to God’s commandments.</span>",
      "marker_line_index": 44,
      "placement_method": "fallback_anchor_start",
      "placement_score": 3,
      "matched_snippet": "עמודי היכא דהוו גרסי &star ואמר רבי חייא בר אמי משמיה דעולא גדול הנהנה מיגיעו יותר מירא שמים",
      "source_kind": "commentary_link"
    },
    {
      "ref": "Psalms 128:2",
      "he_ref": "תהילים קכ״ח:ב׳",
      "url": "https://www.sefaria.org/Psalms_128%3A2?lang=bi",
      "segment_ids": [
        20
      ],
      "anchor_refs": [
        "Berakhot 8a:21"
      ],
      "hebrew": "יְגִ֣יעַ כַּ֭פֶּיךָ כִּ֣י תֹאכֵ֑ל אַ֝שְׁרֶ֗יךָ וְט֣וֹב לָֽךְ׃",
      "english": "<span class=\"poetry indentAll\">You shall enjoy the fruit of your labors;</span><br><span class=\"poetry indentAllDouble\">you shall be happy and you shall prosper.</span>",
      "marker_line_index": 46,
      "placement_method": "quote_match",
      "placement_score": 29,
      "matched_snippet": "תאכל אשריך וטוב לך אשריך בעולם הזה וטוב לך לעולם הבא ולגבי ירא שמים וטוב לך לא כתיב ביה",
      "source_kind": "commentary_link"
    },
    {
      "ref": "I Kings 2",
      "he_ref": "מלכים א ב׳",
      "url": "https://www.sefaria.org/I_Kings_2?lang=bi",
      "segment_ids": [
        21
      ],
      "anchor_refs": [
        "Berakhot 8a:22"
      ],
      "hebrew": "וַיִּקְרְב֥וּ יְמֵֽי־דָוִ֖ד לָמ֑וּת וַיְצַ֛ו אֶת־שְׁלֹמֹ֥ה בְנ֖וֹ לֵאמֹֽר׃ אָנֹכִ֣י הֹלֵ֔ךְ בְּדֶ֖רֶךְ כׇּל־הָאָ֑רֶץ וְחָזַקְתָּ֖ וְהָיִ֥יתָֽ לְאִֽישׁ׃ וְשָׁמַרְתָּ֞ אֶת־מִשְׁמֶ֣רֶת&thinsp;<b>׀</b> יְהֹוָ֣ה אֱלֹהֶ֗יךָ לָלֶ֤כֶת בִּדְרָכָיו֙ לִשְׁמֹ֨ר חֻקֹּתָ֤יו מִצְוֺתָיו֙ וּמִשְׁפָּטָ֣יו וְעֵדְוֺתָ֔יו כַּכָּת֖וּב בְּתוֹרַ֣ת מֹשֶׁ֑ה לְמַ֣עַן תַּשְׂכִּ֗יל אֵ֚ת כׇּל־אֲשֶׁ֣ר תַּעֲשֶׂ֔ה וְאֵ֛ת כׇּל־אֲשֶׁ֥ר תִּפְנֶ֖ה שָֽׁם׃ לְמַ֩עַן֩ יָקִ֨ים יְהֹוָ֜ה אֶת־דְּבָר֗וֹ אֲשֶׁ֨ר דִּבֶּ֣ר עָלַי֮ לֵאמֹר֒ אִם־יִשְׁמְר֨וּ בָנֶ֜יךָ אֶת־דַּרְכָּ֗ם לָלֶ֤כֶת לְפָנַי֙ בֶּאֱמֶ֔ת בְּכׇל־לְבָבָ֖ם וּבְכׇל־נַפְשָׁ֑ם לֵאמֹ֕ר לֹֽא־יִכָּרֵ֤ת לְךָ֙ אִ֔ישׁ מֵעַ֖ל כִּסֵּ֥א יִשְׂרָאֵֽל׃ וְגַ֣ם אַתָּ֣ה יָדַ֡עְתָּ אֵת֩ אֲשֶׁר־עָ֨שָׂה לִ֜י יוֹאָ֣ב בֶּן־צְרוּיָ֗ה אֲשֶׁ֣ר עָשָׂ֣ה לִשְׁנֵֽי־שָׂרֵ֣י צִבְא֣וֹת יִ֠שְׂרָאֵ֠ל לְאַבְנֵ֨ר בֶּן־נֵ֜ר וְלַעֲמָשָׂ֤א בֶן־יֶ֙תֶר֙ וַיַּ֣הַרְגֵ֔ם וַיָּ֥שֶׂם דְּמֵֽי־מִלְחָמָ֖ה בְּשָׁלֹ֑ם וַיִּתֵּ֞ן דְּמֵ֣י מִלְחָמָ֗ה בַּחֲגֹֽרָתוֹ֙ אֲשֶׁ֣ר בְּמׇתְנָ֔יו וּֽבְנַעֲל֖וֹ אֲשֶׁ֥ר בְּרַגְלָֽיו׃ וְעָשִׂ֖יתָ כְּחׇכְמָתֶ֑ךָ וְלֹֽא־תוֹרֵ֧ד שֵׂיבָת֛וֹ בְּשָׁלֹ֖ם שְׁאֹֽל׃ וְלִבְנֵ֨י בַרְזִלַּ֤י הַגִּלְעָדִי֙ תַּֽעֲשֶׂה־חֶ֔סֶד וְהָי֖וּ בְּאֹכְלֵ֣י שֻׁלְחָנֶ֑ךָ כִּי־כֵן֙ קָרְב֣וּ אֵלַ֔י בְּבׇרְחִ֕י מִפְּנֵ֖י אַבְשָׁל֥וֹם אָחִֽיךָ׃ וְהִנֵּ֣ה עִ֠מְּךָ֠ שִֽׁמְעִ֨י בֶן־גֵּרָ֥א בֶֽן־הַיְמִינִי֮ מִבַּחֻרִים֒ וְה֤וּא קִֽלְלַ֙נִי֙ קְלָלָ֣ה נִמְרֶ֔צֶת בְּי֖וֹם לֶכְתִּ֣י מַחֲנָ֑יִם וְהֽוּא־יָרַ֤ד לִקְרָאתִי֙ הַיַּרְדֵּ֔ן וָאֶשָּׁ֨בַֽע ל֤וֹ בַֽיהֹוָה֙ לֵאמֹ֔ר אִם־אֲמִֽיתְךָ֖ בֶּחָֽרֶב׃ וְעַתָּה֙ אַל־תְּנַקֵּ֔הוּ כִּ֛י אִ֥ישׁ חָכָ֖ם אָ֑תָּה וְיָֽדַעְתָּ֙ אֵ֣ת אֲשֶׁ֣ר תַּֽעֲשֶׂה־לּ֔וֹ וְהוֹרַדְתָּ֧ אֶת־שֵׂיבָת֛וֹ בְּדָ֖ם שְׁאֽוֹל׃ וַיִּשְׁכַּ֥ב דָּוִ֖ד עִם־אֲבֹתָ֑יו וַיִּקָּבֵ֖ר בְּעִ֥יר דָּוִֽד׃&nbsp;<span class=\"mam-spi-pe\">{פ}</span><br> וְהַיָּמִ֗ים אֲשֶׁ֨ר מָלַ֤ךְ דָּוִד֙ עַל־יִשְׂרָאֵ֔ל אַרְבָּעִ֖ים שָׁנָ֑ה בְּחֶבְר֤וֹן מָלַךְ֙ שֶׁ֣בַע שָׁנִ֔ים וּבִירוּשָׁלַ֣͏ִם מָלַ֔ךְ שְׁלֹשִׁ֥ים וְשָׁלֹ֖שׁ שָׁנִֽים׃ וּשְׁלֹמֹ֕ה יָשַׁ֕ב עַל־כִּסֵּ֖א דָּוִ֣ד אָבִ֑יו וַתִּכֹּ֥ן מַלְכֻת֖וֹ מְאֹֽד׃&nbsp;<span class=\"mam-spi-samekh\">{ס}</span>&nbsp;&nbsp;&nbsp;&nbsp;&nbsp;&nbsp;&nbsp;&nbsp; וַיָּבֹ֞א אֲדֹנִיָּ֣הוּ בֶן־חַגִּ֗ית אֶל־בַּת־שֶׁ֙בַע֙ אֵם־שְׁלֹמֹ֔ה וַתֹּ֖אמֶר הֲשָׁל֣וֹם בֹּאֶ֑ךָ וַיֹּ֖אמֶר שָׁלֽוֹם׃ וַיֹּ֕אמֶר דָּבָ֥ר לִ֖י אֵלָ֑יִךְ וַתֹּ֖אמֶר דַּבֵּֽר׃ וַיֹּ֗אמֶר אַ֤תְּ יָדַ֙עַתְּ֙ כִּי־לִי֙ הָיְתָ֣ה הַמְּלוּכָ֔ה וְעָלַ֞י שָׂ֧מוּ כׇֽל־יִשְׂרָאֵ֛ל פְּנֵיהֶ֖ם לִמְלֹ֑ךְ וַתִּסֹּ֤ב הַמְּלוּכָה֙ וַתְּהִ֣י לְאָחִ֔י כִּ֥י מֵיְהֹוָ֖ה הָ֥יְתָה לּֽוֹ׃ וְעַתָּ֗ה שְׁאֵלָ֤ה אַחַת֙ אָֽנֹכִי֙ שֹׁאֵ֣ל מֵֽאִתָּ֔ךְ אַל־תָּשִׁ֖בִי אֶת־פָּנָ֑י וַתֹּ֥אמֶר אֵלָ֖יו דַּבֵּֽר׃ וַיֹּ֗אמֶר אִמְרִי־נָא֙ לִשְׁלֹמֹ֣ה הַמֶּ֔לֶךְ כִּ֥י לֹֽא־יָשִׁ֖יב אֶת־פָּנָ֑יִךְ וְיִתֶּן־לִ֛י אֶת־אֲבִישַׁ֥ג הַשּׁוּנַמִּ֖ית לְאִשָּֽׁה׃ וַתֹּ֥אמֶר בַּת־שֶׁ֖בַע ט֑וֹב אָנֹכִ֕י אֲדַבֵּ֥ר עָלֶ֖יךָ אֶל־הַמֶּֽלֶךְ׃ וַתָּבֹ֤א בַת־שֶׁ֙בַע֙ אֶל־הַמֶּ֣לֶךְ שְׁלֹמֹ֔ה לְדַבֶּר־ל֖וֹ עַל־אֲדֹנִיָּ֑הוּ וַיָּ֩קׇם֩ הַמֶּ֨לֶךְ לִקְרָאתָ֜הּ וַיִּשְׁתַּ֣חוּ לָ֗הּ וַיֵּ֙שֶׁב֙ עַל־כִּסְא֔וֹ וַיָּ֤שֶׂם כִּסֵּא֙ לְאֵ֣ם הַמֶּ֔לֶךְ וַתֵּ֖שֶׁב לִימִינֽוֹ׃ וַתֹּ֗אמֶר שְׁאֵלָ֨ה אַחַ֤ת קְטַנָּה֙ אָֽנֹכִי֙ שֹׁאֶ֣לֶת מֵֽאִתָּ֔ךְ אַל־תָּ֖שֶׁב אֶת־פָּנָ֑י וַיֹּֽאמֶר־לָ֤הּ הַמֶּ֙לֶךְ֙ שַׁאֲלִ֣י אִמִּ֔י כִּ֥י לֹא־אָשִׁ֖יב אֶת־פָּנָֽיִךְ׃ וַתֹּ֕אמֶר יֻתַּ֖ן אֶת־אֲבִישַׁ֣ג הַשֻּׁנַמִּ֑ית לַאֲדֹנִיָּ֥הוּ אָחִ֖יךָ לְאִשָּֽׁה׃ וַיַּ֩עַן֩ הַמֶּ֨לֶךְ שְׁלֹמֹ֜ה וַיֹּ֣אמֶר לְאִמּ֗וֹ וְלָמָה֩ אַ֨תְּ שֹׁאֶ֜לֶת אֶת־אֲבִישַׁ֤ג הַשֻּֽׁנַמִּית֙ לַאֲדֹ֣נִיָּ֔הוּ וְשַֽׁאֲלִי־לוֹ֙ אֶת־הַמְּלוּכָ֔ה כִּ֛י ה֥וּא אָחִ֖י הַגָּד֣וֹל מִמֶּ֑נִּי וְלוֹ֙ וּלְאֶבְיָתָ֣ר הַכֹּהֵ֔ן וּלְיוֹאָ֖ב בֶּן־צְרוּיָֽה׃&nbsp;<span class=\"mam-spi-pe\">{פ}</span><br> וַיִּשָּׁבַע֙ הַמֶּ֣לֶךְ שְׁלֹמֹ֔ה בַּיהֹוָ֖ה לֵאמֹ֑ר כֹּ֣ה יַֽעֲשֶׂה־לִּ֤י אֱלֹהִים֙ וְכֹ֣ה יוֹסִ֔יף כִּ֣י בְנַפְשׁ֔וֹ דִּבֶּר֙ אֲדֹ֣נִיָּ֔הוּ אֶת־הַדָּבָ֖ר הַזֶּֽה׃ וְעַתָּ֗ה חַי־יְהֹוָה֙ אֲשֶׁ֣ר הֱכִינַ֗נִי <span class=\"mam-kq\"><span class=\"mam-kq-k\">(ויושיביני)</span> <span class=\"mam-kq-q\">[וַיּֽוֹשִׁיבַ֙נִי֙]</span></span> עַל־כִּסֵּא֙ דָּוִ֣ד אָבִ֔י וַאֲשֶׁ֧ר עָשָׂה־לִ֛י בַּ֖יִת כַּאֲשֶׁ֣ר דִּבֵּ֑ר כִּ֣י הַיּ֔וֹם יוּמַ֖ת אֲדֹנִיָּֽהוּ׃ וַיִּשְׁלַח֙ הַמֶּ֣לֶךְ שְׁלֹמֹ֔ה בְּיַ֖ד בְּנָיָ֣הוּ בֶן־יְהוֹיָדָ֑ע וַיִּפְגַּע־בּ֖וֹ וַיָּמֹֽת׃&nbsp;<span class=\"mam-spi-samekh\">{ס}</span>&nbsp;&nbsp;&nbsp;&nbsp;&nbsp;&nbsp;&nbsp;&nbsp; וּלְאֶבְיָתָ֨ר הַכֹּהֵ֜ן אָמַ֣ר הַמֶּ֗לֶךְ עֲנָתֹת֙ לֵ֣ךְ עַל־שָׂדֶ֔יךָ כִּ֛י אִ֥ישׁ מָ֖וֶת אָ֑תָּה וּבַיּ֨וֹם הַזֶּ֜ה לֹ֣א אֲמִיתֶ֗ךָ כִּֽי־נָשָׂ֜אתָ אֶת־אֲר֨וֹן אֲדֹנָ֤י יֱהֹוִה֙ לִפְנֵי֙ דָּוִ֣ד אָבִ֔י וְכִ֣י הִתְעַנִּ֔יתָ בְּכֹ֥ל אֲשֶֽׁר־הִתְעַנָּ֖ה אָבִֽי׃ וַיְגָ֤רֶשׁ שְׁלֹמֹה֙ אֶת־אֶבְיָתָ֔ר מִֽהְי֥וֹת כֹּהֵ֖ן לַיהֹוָ֑ה לְמַלֵּא֙ אֶת־דְּבַ֣ר יְהֹוָ֔ה אֲשֶׁ֥ר דִּבֶּ֛ר עַל־בֵּ֥ית עֵלִ֖י בְּשִׁלֹֽה׃&nbsp;<span class=\"mam-spi-pe\">{פ}</span><br> וְהַשְּׁמֻעָה֙ בָּ֣אָה עַד־יוֹאָ֔ב כִּ֣י יוֹאָ֗ב נָטָה֙ אַחֲרֵ֣י אֲדֹנִיָּ֔ה וְאַחֲרֵ֥י אַבְשָׁל֖וֹם לֹ֣א נָטָ֑ה וַיָּ֤נׇס יוֹאָב֙ אֶל־אֹ֣הֶל יְהֹוָ֔ה וַֽיַּחֲזֵ֖ק בְּקַרְנ֥וֹת הַמִּזְבֵּֽחַ׃ וַיֻּגַּ֞ד לַמֶּ֣לֶךְ שְׁלֹמֹ֗ה כִּ֣י נָ֤ס יוֹאָב֙ אֶל־אֹ֣הֶל יְהֹוָ֔ה וְהִנֵּ֖ה אֵ֣צֶל הַמִּזְבֵּ֑חַ וַיִּשְׁלַ֨ח שְׁלֹמֹ֜ה אֶת־בְּנָיָ֧הוּ בֶן־יְהוֹיָדָ֛ע לֵאמֹ֖ר לֵ֥ךְ פְּגַע־בּֽוֹ׃ וַיָּבֹ֨א בְנָיָ֜הוּ אֶל־אֹ֣הֶל יְהֹוָ֗ה וַיֹּ֨אמֶר אֵלָ֜יו כֹּֽה־אָמַ֤ר הַמֶּ֙לֶךְ֙ צֵ֔א וַיֹּ֥אמֶֽר&thinsp;<small>׀</small>&thinsp;לֹ֖א כִּ֣י פֹ֣ה אָמ֑וּת וַיָּ֨שֶׁב בְּנָיָ֤הוּ אֶת־הַמֶּ֙לֶךְ֙ דָּבָ֣ר לֵאמֹ֔ר כֹּֽה־דִבֶּ֥ר יוֹאָ֖ב וְכֹ֥ה עָנָֽנִי׃ וַיֹּ֧אמֶר ל֣וֹ הַמֶּ֗לֶךְ עֲשֵׂה֙ כַּאֲשֶׁ֣ר דִּבֶּ֔ר וּפְגַע־בּ֖וֹ וּקְבַרְתּ֑וֹ וַהֲסִירֹ֣תָ&thinsp;<b>׀</b> דְּמֵ֣י חִנָּ֗ם אֲשֶׁר֙ שָׁפַ֣ךְ יוֹאָ֔ב מֵעָלַ֕י וּמֵעַ֖ל בֵּ֥ית אָבִֽי׃ וְהֵשִׁיב֩ יְהֹוָ֨ה אֶת־דָּמ֜וֹ עַל־רֹאשׁ֗וֹ אֲשֶׁ֣ר פָּגַ֣ע בִּשְׁנֵֽי־אֲ֠נָשִׁ֠ים צַדִּקִ֨ים וְטֹבִ֤ים מִמֶּ֙נּוּ֙ וַיַּהַרְגֵ֣ם בַּחֶ֔רֶב וְאָבִ֥י דָוִ֖ד לֹ֣א יָדָ֑ע אֶת־אַבְנֵ֤ר בֶּן־נֵר֙ שַׂר־צְבָ֣א יִשְׂרָאֵ֔ל וְאֶת־עֲמָשָׂ֥א בֶן־יֶ֖תֶר שַׂר־צְבָ֥א יְהוּדָֽה׃ וְשָׁ֤בוּ דְמֵיהֶם֙ בְּרֹ֣אשׁ יוֹאָ֔ב וּבְרֹ֥אשׁ זַרְע֖וֹ לְעֹלָ֑ם וּלְדָוִ֡ד וּ֠לְזַרְע֠וֹ וּלְבֵית֨וֹ וּלְכִסְא֜וֹ יִהְיֶ֥ה שָׁל֛וֹם עַד־עוֹלָ֖ם מֵעִ֥ם יְהֹוָֽה׃ וַיַּ֗עַל בְּנָיָ֙הוּ֙ בֶּן־יְה֣וֹיָדָ֔ע וַיִּפְגַּע־בּ֖וֹ וַיְמִתֵ֑הוּ וַיִּקָּבֵ֥ר בְּבֵית֖וֹ בַּמִּדְבָּֽר׃ וַיִּתֵּ֨ן הַמֶּ֜לֶךְ אֶת־בְּנָיָ֧הוּ בֶן־יְהוֹיָדָ֛ע תַּחְתָּ֖יו עַל־הַצָּבָ֑א וְאֶת־צָד֤וֹק הַכֹּהֵן֙ נָתַ֣ן הַמֶּ֔לֶךְ תַּ֖חַת אֶבְיָתָֽר׃ וַיִּשְׁלַ֤ח הַמֶּ֙לֶךְ֙ וַיִּקְרָ֣א לְשִׁמְעִ֔י וַיֹּ֣אמֶר ל֗וֹ בְּֽנֵה־לְךָ֥ בַ֙יִת֙ בִּיר֣וּשָׁלַ֔͏ִם וְיָשַׁבְתָּ֖ שָׁ֑ם וְלֹא־תֵצֵ֥א מִשָּׁ֖ם אָ֥נֶה וָאָֽנָה׃ וְהָיָ֣ה&thinsp;<b>׀</b> בְּי֣וֹם צֵאתְךָ֗ וְעָֽבַרְתָּ֙ אֶת־נַ֣חַל קִדְר֔וֹן יָדֹ֥עַ תֵּדַ֖ע כִּ֣י מ֣וֹת תָּמ֑וּת דָּמְךָ֖ יִהְיֶ֥ה בְרֹאשֶֽׁךָ׃ וַיֹּ֨אמֶר שִׁמְעִ֤י לַמֶּ֙לֶךְ֙ ט֣וֹב הַדָּבָ֔ר כַּאֲשֶׁ֤ר דִּבֶּר֙ אֲדֹנִ֣י הַמֶּ֔לֶךְ כֵּ֖ן יַעֲשֶׂ֣ה עַבְדֶּ֑ךָ וַיֵּ֧שֶׁב שִׁמְעִ֛י בִּירוּשָׁלַ֖͏ִם יָמִ֥ים רַבִּֽים׃&nbsp;<span class=\"mam-spi-samekh\">{ס}</span>&nbsp;&nbsp;&nbsp;&nbsp;&nbsp;&nbsp;&nbsp;&nbsp; וַיְהִ֗י מִקֵּץ֙ שָׁלֹ֣שׁ שָׁנִ֔ים וַיִּבְרְח֤וּ שְׁנֵֽי־עֲבָדִים֙ לְשִׁמְעִ֔י אֶל־אָכִ֥ישׁ בֶּֽן־מַעֲכָ֖ה מֶ֣לֶךְ גַּ֑ת וַיַּגִּ֤ידוּ לְשִׁמְעִי֙ לֵאמֹ֔ר הִנֵּ֥ה עֲבָדֶ֖יךָ בְּגַֽת׃ וַיָּ֣קׇם שִׁמְעִ֗י וַֽיַּחֲבֹשׁ֙ אֶת־חֲמֹר֔וֹ וַיֵּ֤לֶךְ גַּ֙תָה֙ אֶל־אָכִ֔ישׁ לְבַקֵּ֖שׁ אֶת־עֲבָדָ֑יו וַיֵּ֣לֶךְ שִׁמְעִ֔י וַיָּבֵ֥א אֶת־עֲבָדָ֖יו מִגַּֽת׃&nbsp;<span class=\"mam-spi-samekh\">{ס}</span>&nbsp;&nbsp;&nbsp;&nbsp;&nbsp;&nbsp;&nbsp;&nbsp; וַיֻּגַּ֖ד לִשְׁלֹמֹ֑ה כִּי־הָלַ֨ךְ שִׁמְעִ֧י מִירוּשָׁלַ֛͏ִם גַּ֖ת וַיָּשֹֽׁב׃ וַיִּשְׁלַ֨ח הַמֶּ֜לֶךְ וַיִּקְרָ֣א לְשִׁמְעִ֗י וַיֹּ֨אמֶר אֵלָ֜יו הֲל֧וֹא הִשְׁבַּעְתִּ֣יךָ בַיהֹוָ֗ה וָאָעִ֤ד בְּךָ֙ לֵאמֹ֔ר בְּי֣וֹם צֵאתְךָ֗ וְהָֽלַכְתָּ֙ אָ֣נֶה וָאָ֔נָה יָדֹ֥עַ תֵּדַ֖ע כִּ֣י מ֣וֹת תָּמ֑וּת וַתֹּ֧אמֶר אֵלַ֛י ט֥וֹב הַדָּבָ֖ר שָׁמָֽעְתִּי׃ וּמַדּ֕וּעַ לֹ֣א שָׁמַ֔רְתָּ אֵ֖ת שְׁבֻעַ֣ת יְהֹוָ֑ה וְאֶת־הַמִּצְוָ֖ה אֲשֶׁר־צִוִּ֥יתִי עָלֶֽיךָ׃ וַיֹּ֨אמֶר הַמֶּ֜לֶךְ אֶל־שִׁמְעִ֗י אַתָּ֤ה יָדַ֙עְתָּ֙ אֵ֣ת כׇּל־הָרָעָ֗ה אֲשֶׁ֤ר יָדַע֙ לְבָ֣בְךָ֔ אֲשֶׁ֥ר עָשִׂ֖יתָ לְדָוִ֣ד אָבִ֑י וְהֵשִׁ֧יב יְהֹוָ֛ה אֶת־רָעָתְךָ֖ בְּרֹאשֶֽׁךָ׃ וְהַמֶּ֥לֶךְ שְׁלֹמֹ֖ה בָּר֑וּךְ וְכִסֵּ֣א דָוִ֗ד יִהְיֶ֥ה נָכ֛וֹן לִפְנֵ֥י יְהֹוָ֖ה עַד־עוֹלָֽם׃ וַיְצַ֣ו הַמֶּ֗לֶךְ אֶת־בְּנָיָ֙הוּ֙ בֶּן־יְה֣וֹיָדָ֔ע וַיֵּצֵ֕א וַיִּפְגַּע־בּ֖וֹ וַיָּמֹ֑ת וְהַמַּמְלָכָ֥ה נָכ֖וֹנָה בְּיַד־שְׁלֹמֹֽה׃",
      "english": "When David’s life was drawing to a close, he instructed his son Solomon as follows: “I am going the way of all the earth; you will be the man in charge—if you act with determination.<sup class=\"footnote-marker\">a</sup><i class=\"footnote\"><b>you will be the man in charge—if you act with determination </b>Or “be strong and show yourself a man.”</i> Keep the charge of the E<small>TERNAL</small> your God, walking in God’s ways and following God’s laws, commandments, rules, and admonitions as recorded in the Teaching of Moses, in order that you may succeed in whatever you undertake and wherever you turn. Then G<small>OD</small> will fulfill the promise that was made concerning me: ‘If your descendants are scrupulous in their conduct, and walk before Me faithfully, with all their heart and soul, your line on the throne of Israel shall never end!’<sup class=\"footnote-marker\">b</sup><i class=\"footnote\"><b>your line on the throne…shall never end </b>Lit. “there shall never cease to be a man of yours on the throne,” i.e., ruling on your behalf. Cf. 2 Sam. 7.12–16.</i> “Further, you know what Joab son of Zeruiah did to me, what he did to the two commanders of Israel’s forces, Abner son of Ner and Amasa son of Jether: he killed them, shedding<sup class=\"footnote-marker\">c</sup><i class=\"footnote\"><b>shedding </b>Meaning of Heb. uncertain.</i> blood of war in peacetime, staining the girdle of his loins and the sandals on his feet with blood of war.<sup class=\"footnote-marker\">d</sup><i class=\"footnote\"><b>staining … with blood of war </b>I.e., Joab had thus brought bloodguilt on David’s house; see 2 Sam. 3.27; 20.10.</i> So act in accordance with your wisdom, and see that his white hair does not go down to Sheol in peace. “But deal graciously with the sons of Barzillai the Gileadite, for they befriended me when I fled from your brother Absalom; let them be among those that eat at your table.<sup class=\"footnote-marker\">e</sup><i class=\"footnote\"><b>that eat at your table </b>I.e., for whose maintenance you provide; see 2 Sam. 19.32ff.</i> “You must also deal with Shimei son of Gera, the Benjaminite from Bahurim. He insulted me outrageously when I was on my way to Mahanaim; but he came down to meet me at the Jordan,<sup class=\"footnote-marker\">f</sup><i class=\"footnote\"><b>he came down to meet me at the Jordan </b>See 2 Sam. 16.5ff.; 19.17ff.</i> and I swore to him by G<small>OD</small>: ‘I will not put you to the sword.’ So do not let him go unpunished; for you are a shrewd man and you will know how to deal with him and send his gray hair down to Sheol in blood.” So David rested with his ancestors, and he was buried in the City of David. The length of David’s reign over Israel was forty years: he reigned seven years in Hebron, and he reigned thirty-three years in Jerusalem. And Solomon sat upon the throne of his father David, and his rule was firmly established. Adonijah son of Haggith came to see Bathsheba, Solomon’s mother. She said, “Do you come with friendly intent?” “Yes,” he replied; and he continued, “I would like to have a word with you.” “Speak up,” she said. Then he said, “You know that the kingship was rightly mine and that all Israel wanted me to reign. But the kingship passed on to my brother; it came to him by G<small>OD</small>’s will. And now I have one request to make of you; do not refuse me.” She said, “Speak up.” He replied, “Please ask King Solomon—for he won’t refuse you—to give me Abishag the Shunammite as wife.” “Very well,” said Bathsheba, “I will speak to the king in your behalf.” So Bathsheba went to King Solomon to speak to him about Adonijah. The king rose to greet her and bowed down to her. He sat on his throne; and he had a throne placed for the queen mother, and she sat on his right. She said, “I have one small request to make of you, do not refuse me.” He responded, “Ask, Mother; I shall not refuse you.” Then she said, “Let Abishag the Shunammite be given to your brother Adonijah as wife.” The king replied to his mother, “Why request Abishag the Shunammite for Adonijah? Request the kingship for him! For he is my older brother, and the priest Abiathar and Joab son of Zeruiah are on his side.”<sup class=\"footnote-marker\">g</sup><i class=\"footnote\"><b>and the priest Abiathar and Joab son of Zeruiah are on his side </b>Lit. “And for him and for Abiathar and for Joab son of Zeruiah.” Meaning of Heb. uncertain.</i> Thereupon, King Solomon swore by G<small>OD</small>, saying, “So may God do to me and even more, if broaching this matter does not cost Adonijah his life! Now, as G<small>OD</small> lives, who has established me and set me on the throne of my father David and who has provided him<sup class=\"footnote-marker\">h</sup><i class=\"footnote\"><b>him </b>Heb. “me.”</i> with a house, as he promised, Adonijah shall be put to death this very day!” And Solomon instructed Benaiah son of Jehoiada, who struck Adonijah<sup class=\"footnote-marker\">i</sup><i class=\"footnote\"><b>Adonijah </b>Heb. “him.”</i> down; and so he died. To the priest Abiathar, the king said, “Go to your estate at Anathoth! You deserve to die, but I shall not put you to death at this time, because you carried the Ark of my Sovereign G<small>OD</small> before my father David and because you shared all the hardships that my father endured.” So Solomon dismissed Abiathar from his office of priest of G<small>OD</small>—thus fulfilling what G<small>OD</small> had spoken at Shiloh<sup class=\"footnote-marker\">j</sup><i class=\"footnote\"><b>what G<small>OD</small> had spoken at Shiloh </b>Cf. 1 Sam. 3.14.</i> regarding the house of Eli. When the news reached Joab, he fled to the Tent of G<small>OD</small> and grasped the horns of the altar—for Joab had sided with Adonijah, though he had not sided with Absalom. King Solomon was told that Joab had fled to the Tent of G<small>OD</small> and that he was there by the altar; so Solomon sent Benaiah son of Jehoiada, saying, “Go and strike him down.” Benaiah went to the Tent of G<small>OD</small> and said to him, “Thus said the king: Come out!” “No!” he replied; “I will die here.” Benaiah reported back to the king that Joab had answered thus and thus, and the king said, “Do just as he said; strike him down and bury him, and remove guilt from me and my father’s house for the blood of the innocent that Joab has shed. Thus G<small>OD</small> will bring his blood guilt down upon his own head, because, unbeknown to my father, he struck down with the sword two men more righteous and honorable than he—Abner son of Ner, the army commander of Israel, and Amasa son of Jether, the army commander of Judah. May the guilt for their blood come down upon the head of Joab and his descendants forever, and may good fortune from G<small>OD</small> be granted forever to David and his descendants, his house and his throne.” So Benaiah son of Jehoiada went up and struck him down. And he was buried at his home in the wilderness. In his place, the king appointed Benaiah son of Jehoiada over the army, and in place of Abiathar, the king appointed the priest Zadok. Then the king summoned Shimei and said to him, “Build yourself a house in Jerusalem and stay there—do not ever go out from there anywhere else. On the very day that you go out and cross the Wadi Kidron, you can be sure that you will die; your blood shall be on your own head.” “That is fair,” said Shimei to the king, “your servant will do just as my lord the king has spoken.” And for a long time, Shimei remained in Jerusalem. Three years later, two slaves of Shimei ran away to King Achish son of Maacah of Gath. Shimei was told, “Your slaves are in Gath.” Shimei thereupon saddled his donkey and went to Achish in Gath to claim his slaves; and Shimei returned from Gath with his slaves. Solomon was told that Shimei had gone from Jerusalem to Gath and back, and the king summoned Shimei and said to him, “Did I not adjure you by G<small>OD</small> and warn you, ‘On the very day that you leave and go anywhere else, you can be sure that you will die,’ and did you not say to me, ‘It is fair; I accept’? Why did you not abide by the oath before G<small>OD</small> and by the orders that I gave you?” The king said further to Shimei, “You know all the wrong, which you remember very well, that you did to my father David. Now G<small>OD</small> brings down your wrongdoing upon your own head. But King Solomon shall be blessed, and the throne of David shall be established before G<small>OD</small> forever.” The king gave orders to Benaiah son of Jehoiada and he went out and struck Shimei<sup class=\"footnote-marker\">k</sup><i class=\"footnote\"><b>Shimei </b>Heb. “him.”</i> down; and so he died.<br>Thus the kingdom was secured in Solomon’s hands.",
      "marker_line_index": 45,
      "placement_method": "quote_match",
      "placement_score": 40,
      "matched_snippet": "דאילו גבי ירא שמים כתיב אשרי איש ירא את ה ואילו גבי נהנה מיגיעו כתיב יגיע כפיך כי",
      "source_kind": "commentary_link"
    },
    {
      "ref": "Isaiah 1:28",
      "he_ref": "ישעיהו א׳:כ״ח",
      "url": "https://www.sefaria.org/Isaiah_1%3A28?lang=bi",
      "segment_ids": [
        24
      ],
      "anchor_refs": [
        "Berakhot 8a:25"
      ],
      "hebrew": "וְשֶׁ֧בֶר פֹּשְׁעִ֛ים וְחַטָּאִ֖ים יַחְדָּ֑ו וְעֹזְבֵ֥י יְהֹוָ֖ה יִכְלֽוּ׃",
      "english": "<span class=\"poetry indentAll\">But rebels and sinners shall all be crushed,</span><br><span class=\"poetry indentAll\">And those who forsake </span> G<small>OD</small> shall perish.",
      "marker_line_index": 48,
      "placement_method": "fallback_anchor_start",
      "placement_score": 2,
      "matched_snippet": "",
      "source_kind": "commentary_link"
    },
    {
      "ref": "Psalms 55:19",
      "he_ref": "תהילים נ״ה:י״ט",
      "url": "https://www.sefaria.org/Psalms_55%3A19?lang=bi",
      "segment_ids": [
        2
      ],
      "anchor_refs": [
        "Berakhot 8a:3"
      ],
      "hebrew": "פָּ֘דָ֤ה בְשָׁל֣וֹם נַ֭פְשִׁי מִקְּרׇב־לִ֑י כִּֽי־בְ֝רַבִּ֗ים הָי֥וּ עִמָּדִֽי׃",
      "english": "<span class=\"poetry indentAll\">[God] redeems me unharmed</span><br><span class=\"poetry indentAllDouble\">from the battle against me;</span><br><span class=\"poetry indentAllDouble\">it is as though many are on my side.<sup class=\"footnote-marker\">a</sup><i class=\"footnote\"><b>it is as though many are on my side </b>Meaning of Heb. uncertain.</i> </span>",
      "marker_line_index": 8,
      "placement_method": "quote_match",
      "placement_score": 16,
      "matched_snippet": "ולא ימאס וכתיב פדה בשלום נפשי מקרב לי",
      "source_kind": "commentary_link"
    },
    {
      "ref": "Proverbs 3:17",
      "he_ref": "משלי ג׳:י״ז",
      "url": "https://www.sefaria.org/Proverbs_3%3A17?lang=bi",
      "segment_ids": [
        3
      ],
      "anchor_refs": [
        "Berakhot 8a:4"
      ],
      "hebrew": "דְּרָכֶ֥יהָ דַרְכֵי־נֹ֑עַם וְֽכׇל־נְתִ֖יבוֹתֶ֣יהָ שָׁלֽוֹם׃",
      "english": "<span class=\"poetry indentAll\">Her ways are pleasant ways,</span><br><span class=\"poetry indentAll\">And all her paths, peaceful.</span>",
      "marker_line_index": 6,
      "placement_method": "fallback_anchor_start",
      "placement_score": 3,
      "matched_snippet": "ולא ימאס וכתיב פדה בשלום נפשי מקרב לי",
      "source_kind": "commentary_link"
    },
    {
      "ref": "Jeremiah 12:14",
      "he_ref": "ירמיהו י״ב:י״ד",
      "url": "https://www.sefaria.org/Jeremiah_12%3A14?lang=bi",
      "segment_ids": [
        4
      ],
      "anchor_refs": [
        "Berakhot 8a:5"
      ],
      "hebrew": "כֹּ֣ה&thinsp;<b>׀</b> אָמַ֣ר יְהֹוָ֗ה עַל־כׇּל־שְׁכֵנַי֙ הָֽרָעִ֔ים הַנֹּֽגְעִים֙ בַּֽנַּחֲלָ֔ה אֲשֶׁר־הִנְחַ֥לְתִּי אֶת־עַמִּ֖י אֶת־יִשְׂרָאֵ֑ל הִנְנִ֤י נֹֽתְשָׁם֙ מֵעַ֣ל אַדְמָתָ֔ם וְאֶת־בֵּ֥ית יְהוּדָ֖ה אֶתּ֥וֹשׁ מִתּוֹכָֽם׃",
      "english": "Thus said G<small>OD</small>: As for My wicked neighbors who encroach on the heritage that I gave to My people Israel—I am going to uproot them from their soil, and I will uproot the House of Judah out of the midst of them.",
      "marker_line_index": 13,
      "placement_method": "quote_match",
      "placement_score": 19,
      "matched_snippet": "שנאמר כה אמר ה על כל שכני הרעים הנגעים בנחלה אשר הנחלתי את",
      "source_kind": "commentary_link"
    },
    {
      "ref": "Proverbs 8:34",
      "he_ref": "משלי ח׳:ל״ד",
      "url": "https://www.sefaria.org/Proverbs_8%3A34?lang=bi",
      "segment_ids": [
        6
      ],
      "anchor_refs": [
        "Berakhot 8a:7"
      ],
      "hebrew": "אַ֥שְֽׁרֵי<span class=\"mam-implicit-maqaf\">־</span>אָדָם֮ שֹׁמֵ֢עַֽ֫ לִ֥י לִשְׁקֹ֣ד עַל־דַּ֭לְתֹתַי י֤וֹם&thinsp;<b>׀</b> י֑וֹם לִ֝שְׁמֹ֗ר מְזוּזֹ֥ת פְּתָחָֽי׃",
      "english": "<span class=\"poetry indentAll\">Happy is the one who listens to me,</span><br><span class=\"poetry indentAll\">Coming early to my gates each day,</span><br><span class=\"poetry indentAll\">Waiting outside my doors.</span>",
      "marker_line_index": 19,
      "placement_method": "quote_match",
      "placement_score": 40,
      "matched_snippet": "דתורכו חיי אמר רבי אחא ברבי חנינא מאי קרא אשרי אדם שמע לי לשקד על",
      "source_kind": "commentary_link"
    },
    {
      "ref": "Proverbs 8:35",
      "he_ref": "משלי ח׳:ל״ה",
      "url": "https://www.sefaria.org/Proverbs_8%3A35?lang=bi",
      "segment_ids": [
        6
      ],
      "anchor_refs": [
        "Berakhot 8a:7"
      ],
      "hebrew": "כִּ֣י מֹ֭צְאִי <span class=\"mam-kq\"><span class=\"mam-kq-k\">(מצאי)</span> <span class=\"mam-kq-q\">[מָצָ֣א]</span></span> חַיִּ֑ים וַיָּ֥פֶק רָ֝צ֗וֹן מֵיְהֹוָֽה׃",
      "english": "<span class=\"poetry indentAll\">For one who finds me finds life</span><br><span class=\"poetry indentAll\">And obtains favor from G<small>OD</small>.</span>",
      "marker_line_index": 20,
      "placement_method": "quote_match",
      "placement_score": 21,
      "matched_snippet": "דלתתי יום יום לשמור מזוזת פתחי וכתיב בתריה כי מצאי מצא חיים &star אמר",
      "source_kind": "commentary_link"
    },
    {
      "ref": "Psalms 32:6",
      "he_ref": "תהילים ל״ב:ו׳",
      "url": "https://www.sefaria.org/Psalms_32%3A6?lang=bi",
      "segment_ids": [
        8
      ],
      "anchor_refs": [
        "Berakhot 8a:9"
      ],
      "hebrew": "עַל־זֹ֡את יִתְפַּלֵּ֬ל כׇּל־חָסִ֨יד&thinsp;<b>׀</b> אֵלֶיךָ֮ לְעֵ֢ת מְ֫צֹ֥א רַ֗ק לְ֭שֵׁטֶף מַ֣יִם רַבִּ֑ים אֵ֝לָ֗יו לֹ֣א יַגִּֽיעוּ׃",
      "english": "<span class=\"poetry indentAll\">Therefore let all the faithful pray to You</span><br><span class=\"poetry indentAllDouble\">upon discovering [their sin],<sup class=\"footnote-marker\">b</sup><i class=\"footnote\"><b>upon discovering [their sin] </b>Meaning of Heb. uncertain; in contrast to others “in a time when You may be found.”</i> </span><br><span class=\"poetry indentAllDouble\">that the rushing mighty waters</span><br><span class=\"poetry indentAllDouble\">not overtake them.</span>",
      "marker_line_index": 23,
      "placement_method": "quote_match",
      "placement_score": 18,
      "matched_snippet": "אליך לעת מצא אמר רבי חנינא לעת מצא זו אשה שנאמר מצא אשה מצא טוב",
      "source_kind": "commentary_link"
    },
    {
      "ref": "Proverbs 18:22",
      "he_ref": "משלי י״ח:כ״ב",
      "url": "https://www.sefaria.org/Proverbs_18%3A22?lang=bi",
      "segment_ids": [
        8
      ],
      "anchor_refs": [
        "Berakhot 8a:9"
      ],
      "hebrew": "מָצָ֣א אִ֭שָּׁה מָ֣צָא ט֑וֹב וַיָּ֥פֶק רָ֝צ֗וֹן מֵיְהֹוָֽה׃",
      "english": "<span class=\"poetry indentAll\">He who finds a wife has found happiness</span><br><span class=\"poetry indentAll\">And has won G<small>OD</small>’s favor.</span>",
      "marker_line_index": 25,
      "placement_method": "quote_match",
      "placement_score": 39,
      "matched_snippet": "אשה מצא טוב ויפק רצון מה מוצא דכתיב ומוצא אני מר ממות את האשה",
      "source_kind": "commentary_link"
    }
  ],
  "summary": {
    "direct_quote_count": 7,
    "commentary_link_count": 15,
    "total_candidate_count": 22
  }
}