{
  "metadata": {
    "masechet": "sanhedrin",
    "masechet_he": "סנהדרין",
    "daf": "104b",
    "source": [
      "rashi_girsa"
    ],
    "schema_version": 1,
    "generated_by": "tzurat/rashi_recension/",
    "counts": {
      "segments_changed": 1,
      "changes": 10,
      "applied": 10,
      "by_type": {
        "orthographic": 1,
        "prefix": 5,
        "suffix": 3,
        "substitution": 1
      },
      "by_confidence": {
        "low": 1,
        "medium": 9
      },
      "by_source": {
        "rashi_girsa": 10
      },
      "skipped_abbrev": 0
    }
  },
  "segments": [
    {
      "segment_id": 8,
      "original_text": "עַמִּי מֵחַטַּאת סְדֹם וְכִי מַשּׂוֹא פָּנִים יֵשׁ בַּדָּבָר אָמַר רָבָא אָמַר רַבִּי יוֹחָנָן מִדָּה יְתֵירָה הָיְתָה בִּירוּשָׁלַיִם שֶׁלֹּא הָיְתָה בִּסְדוֹם דְּאִילּוּ בִּסְדוֹם כְּתִיב הִנֵּה זֶה הָיָה עֲוֹן סְדֹם אֲחוֹתֵךְ גָּאוֹן שִׂבְעַת לֶחֶם וְיַד עָנִי וְאֶבְיוֹן",
      "reconstructed_text": "עַמִּי מֵחַטַּאת סְדֹום וְכִי מַשּׂוֹא פָּנִים יֵשׁ בַּדָּבָר אָמַר רָבָא אָמַר והואיל וישראל רעים יְותרָ מסדום לַמה לֹּא נהָפכו כסְדוֹם דְּאִילּוּ בִּסְדוֹם כְּתִיב הִנֵּה זֶה הָיָה עֲוֹן סְדֹם אֲחוֹתֵךְ גָּאוֹן שִׂבְעַת לֶחֶם וְיַד עָנִי וְאֶבְיוֹן",
      "reconstructed_html": "עַמִּי מֵחַטַּאת <span class=\"girsa-change\" data-change-type=\"orthographic\" data-confidence=\"low\" data-source=\"rashi_girsa\" data-source-ref=\"Rashi on Sanhedrin 104b:8:4\" data-marker=\"הכי גרסינן\" data-original=\"סְדֹם\">סְדֹ<span class=\"girsa-letter-ins\">ו</span>ם</span> וְכִי מַשּׂוֹא פָּנִים יֵשׁ בַּדָּבָר אָמַר רָבָא אָמַר <span class=\"girsa-change\" data-change-type=\"prefix\" data-confidence=\"medium\" data-source=\"rashi_girsa\" data-source-ref=\"Rashi on Sanhedrin 104b:8:4\" data-marker=\"הכי גרסינן\" data-original=\"רַבִּי\"><span class=\"girsa-letter-ins\">ו</span><span class=\"girsa-letter-ins\">ה</span><span class=\"girsa-letter-sub\">ו</span><span class=\"girsa-letter-sub\">א</span>י<span class=\"girsa-letter-ins\">ל</span></span> <span class=\"girsa-change\" data-change-type=\"prefix\" data-confidence=\"medium\" data-source=\"rashi_girsa\" data-source-ref=\"Rashi on Sanhedrin 104b:8:4\" data-marker=\"הכי גרסינן\" data-original=\"יוֹחָנָן\"><span class=\"girsa-letter-ins\">ו</span>י<span class=\"girsa-letter-sub\">ש</span><span class=\"girsa-letter-sub\">ר</span><span class=\"girsa-letter-sub\">א</span><span class=\"girsa-letter-sub\">ל</span></span> <span class=\"girsa-change\" data-change-type=\"suffix\" data-confidence=\"medium\" data-source=\"rashi_girsa\" data-source-ref=\"Rashi on Sanhedrin 104b:8:4\" data-marker=\"הכי גרסינן\" data-original=\"מִדָּה\"><span class=\"girsa-letter-ins\">ר</span><span class=\"girsa-letter-sub\">ע</span><span class=\"girsa-letter-sub\">י</span><span class=\"girsa-letter-sub\">ם</span></span> <span class=\"girsa-change\" data-change-type=\"suffix\" data-confidence=\"medium\" data-source=\"rashi_girsa\" data-source-ref=\"Rashi on Sanhedrin 104b:8:4\" data-marker=\"הכי גרסינן\" data-original=\"יְתֵירָה\">יְ<span class=\"girsa-letter-sub\">ו</span><span class=\"girsa-letter-sub\">ת</span>רָ<span class=\"girsa-letter-del\">ה</span></span> <span class=\"girsa-change\" data-change-type=\"prefix\" data-confidence=\"medium\" data-source=\"rashi_girsa\" data-source-ref=\"Rashi on Sanhedrin 104b:8:4\" data-marker=\"הכי גרסינן\" data-original=\"הָיְתָה\"><span class=\"girsa-letter-ins\">מ</span><span class=\"girsa-letter-sub\">ס</span><span class=\"girsa-letter-sub\">ד</span><span class=\"girsa-letter-sub\">ו</span><span class=\"girsa-letter-sub\">ם</span></span> <span class=\"girsa-change\" data-change-type=\"prefix\" data-confidence=\"medium\" data-source=\"rashi_girsa\" data-source-ref=\"Rashi on Sanhedrin 104b:8:4\" data-marker=\"הכי גרסינן\" data-original=\"בִּירוּשָׁלַיִם\"><span class=\"girsa-letter-del\">בִּ</span><span class=\"girsa-letter-del\">י</span><span class=\"girsa-letter-del\">ר</span><span class=\"girsa-letter-del\">וּ</span><span class=\"girsa-letter-del\">שָׁ</span>לַ<span class=\"girsa-letter-sub\">מ</span><span class=\"girsa-letter-sub\">ה</span></span> <span class=\"girsa-change\" data-change-type=\"prefix\" data-confidence=\"medium\" data-source=\"rashi_girsa\" data-source-ref=\"Rashi on Sanhedrin 104b:8:4\" data-marker=\"הכי גרסינן\" data-original=\"שֶׁלֹּא\"><span class=\"girsa-letter-del\">שֶׁ</span>לֹּא</span> <span class=\"girsa-change\" data-change-type=\"suffix\" data-confidence=\"medium\" data-source=\"rashi_girsa\" data-source-ref=\"Rashi on Sanhedrin 104b:8:4\" data-marker=\"הכי גרסינן\" data-original=\"הָיְתָה\"><span class=\"girsa-letter-ins\">נ</span>הָ<span class=\"girsa-letter-sub\">פ</span><span class=\"girsa-letter-sub\">כ</span><span class=\"girsa-letter-sub\">ו</span></span> <span class=\"girsa-change\" data-change-type=\"substitution\" data-confidence=\"medium\" data-source=\"rashi_girsa\" data-source-ref=\"Rashi on Sanhedrin 104b:8:4\" data-marker=\"הכי גרסינן\" data-original=\"בִּסְדוֹם\"><span class=\"girsa-letter-sub\">כ</span>סְדוֹם</span> דְּאִילּוּ בִּסְדוֹם כְּתִיב הִנֵּה זֶה הָיָה עֲוֹן סְדֹם אֲחוֹתֵךְ גָּאוֹן שִׂבְעַת לֶחֶם וְיַד עָנִי וְאֶבְיוֹן",
      "changes": [
        {
          "type": "orthographic",
          "confidence": "low",
          "apply": true,
          "source": "rashi_girsa",
          "source_ref": "Rashi on Sanhedrin 104b:8:4",
          "marker": "הכי גרסינן",
          "marker_type": "assert",
          "seg_token_index": 2,
          "original": "סְדֹם",
          "proposed": "סדום",
          "recon_text": "סְדֹום",
          "marked_html": "סְדֹ<span class=\"girsa-letter-ins\">ו</span>ם",
          "abbrev": false,
          "proposed_vocalized": false,
          "before_context": "עַמִּי מֵחַטַּאת",
          "after_context": "וְכִי מַשּׂוֹא"
        },
        {
          "type": "prefix",
          "confidence": "medium",
          "apply": true,
          "source": "rashi_girsa",
          "source_ref": "Rashi on Sanhedrin 104b:8:4",
          "marker": "הכי גרסינן",
          "marker_type": "assert",
          "seg_token_index": 11,
          "original": "רַבִּי",
          "proposed": "והואיל",
          "recon_text": "והואיל",
          "marked_html": "<span class=\"girsa-letter-ins\">ו</span><span class=\"girsa-letter-ins\">ה</span><span class=\"girsa-letter-sub\">ו</span><span class=\"girsa-letter-sub\">א</span>י<span class=\"girsa-letter-ins\">ל</span>",
          "abbrev": false,
          "proposed_vocalized": false,
          "before_context": "רָבָא אָמַר",
          "after_context": "יוֹחָנָן מִדָּה"
        },
        {
          "type": "prefix",
          "confidence": "medium",
          "apply": true,
          "source": "rashi_girsa",
          "source_ref": "Rashi on Sanhedrin 104b:8:4",
          "marker": "הכי גרסינן",
          "marker_type": "assert",
          "seg_token_index": 12,
          "original": "יוֹחָנָן",
          "proposed": "וישראל",
          "recon_text": "וישראל",
          "marked_html": "<span class=\"girsa-letter-ins\">ו</span>י<span class=\"girsa-letter-sub\">ש</span><span class=\"girsa-letter-sub\">ר</span><span class=\"girsa-letter-sub\">א</span><span class=\"girsa-letter-sub\">ל</span>",
          "abbrev": false,
          "proposed_vocalized": false,
          "before_context": "אָמַר רַבִּי",
          "after_context": "מִדָּה יְתֵירָה"
        },
        {
          "type": "suffix",
          "confidence": "medium",
          "apply": true,
          "source": "rashi_girsa",
          "source_ref": "Rashi on Sanhedrin 104b:8:4",
          "marker": "הכי גרסינן",
          "marker_type": "assert",
          "seg_token_index": 13,
          "original": "מִדָּה",
          "proposed": "רעים",
          "recon_text": "רעים",
          "marked_html": "<span class=\"girsa-letter-ins\">ר</span><span class=\"girsa-letter-sub\">ע</span><span class=\"girsa-letter-sub\">י</span><span class=\"girsa-letter-sub\">ם</span>",
          "abbrev": false,
          "proposed_vocalized": false,
          "before_context": "רַבִּי יוֹחָנָן",
          "after_context": "יְתֵירָה הָיְתָה"
        },
        {
          "type": "suffix",
          "confidence": "medium",
          "apply": true,
          "source": "rashi_girsa",
          "source_ref": "Rashi on Sanhedrin 104b:8:4",
          "marker": "הכי גרסינן",
          "marker_type": "assert",
          "seg_token_index": 14,
          "original": "יְתֵירָה",
          "proposed": "יותר",
          "recon_text": "יְותרָ",
          "marked_html": "יְ<span class=\"girsa-letter-sub\">ו</span><span class=\"girsa-letter-sub\">ת</span>רָ<span class=\"girsa-letter-del\">ה</span>",
          "abbrev": false,
          "proposed_vocalized": false,
          "before_context": "יוֹחָנָן מִדָּה",
          "after_context": "הָיְתָה בִּירוּשָׁלַיִם"
        },
        {
          "type": "prefix",
          "confidence": "medium",
          "apply": true,
          "source": "rashi_girsa",
          "source_ref": "Rashi on Sanhedrin 104b:8:4",
          "marker": "הכי גרסינן",
          "marker_type": "assert",
          "seg_token_index": 15,
          "original": "הָיְתָה",
          "proposed": "מסדום",
          "recon_text": "מסדום",
          "marked_html": "<span class=\"girsa-letter-ins\">מ</span><span class=\"girsa-letter-sub\">ס</span><span class=\"girsa-letter-sub\">ד</span><span class=\"girsa-letter-sub\">ו</span><span class=\"girsa-letter-sub\">ם</span>",
          "abbrev": false,
          "proposed_vocalized": false,
          "before_context": "מִדָּה יְתֵירָה",
          "after_context": "בִּירוּשָׁלַיִם שֶׁלֹּא"
        },
        {
          "type": "prefix",
          "confidence": "medium",
          "apply": true,
          "source": "rashi_girsa",
          "source_ref": "Rashi on Sanhedrin 104b:8:4",
          "marker": "הכי גרסינן",
          "marker_type": "assert",
          "seg_token_index": 16,
          "original": "בִּירוּשָׁלַיִם",
          "proposed": "למה",
          "recon_text": "לַמה",
          "marked_html": "<span class=\"girsa-letter-del\">בִּ</span><span class=\"girsa-letter-del\">י</span><span class=\"girsa-letter-del\">ר</span><span class=\"girsa-letter-del\">וּ</span><span class=\"girsa-letter-del\">שָׁ</span>לַ<span class=\"girsa-letter-sub\">מ</span><span class=\"girsa-letter-sub\">ה</span>",
          "abbrev": false,
          "proposed_vocalized": false,
          "before_context": "יְתֵירָה הָיְתָה",
          "after_context": "שֶׁלֹּא הָיְתָה"
        },
        {
          "type": "prefix",
          "confidence": "medium",
          "apply": true,
          "source": "rashi_girsa",
          "source_ref": "Rashi on Sanhedrin 104b:8:4",
          "marker": "הכי גרסינן",
          "marker_type": "assert",
          "seg_token_index": 17,
          "original": "שֶׁלֹּא",
          "proposed": "לא",
          "recon_text": "לֹּא",
          "marked_html": "<span class=\"girsa-letter-del\">שֶׁ</span>לֹּא",
          "abbrev": false,
          "proposed_vocalized": false,
          "before_context": "הָיְתָה בִּירוּשָׁלַיִם",
          "after_context": "הָיְתָה בִּסְדוֹם"
        },
        {
          "type": "suffix",
          "confidence": "medium",
          "apply": true,
          "source": "rashi_girsa",
          "source_ref": "Rashi on Sanhedrin 104b:8:4",
          "marker": "הכי גרסינן",
          "marker_type": "assert",
          "seg_token_index": 18,
          "original": "הָיְתָה",
          "proposed": "נהפכו",
          "recon_text": "נהָפכו",
          "marked_html": "<span class=\"girsa-letter-ins\">נ</span>הָ<span class=\"girsa-letter-sub\">פ</span><span class=\"girsa-letter-sub\">כ</span><span class=\"girsa-letter-sub\">ו</span>",
          "abbrev": false,
          "proposed_vocalized": false,
          "before_context": "בִּירוּשָׁלַיִם שֶׁלֹּא",
          "after_context": "בִּסְדוֹם דְּאִילּוּ"
        },
        {
          "type": "substitution",
          "confidence": "medium",
          "apply": true,
          "source": "rashi_girsa",
          "source_ref": "Rashi on Sanhedrin 104b:8:4",
          "marker": "הכי גרסינן",
          "marker_type": "assert",
          "seg_token_index": 19,
          "original": "בִּסְדוֹם",
          "proposed": "כסדום",
          "recon_text": "כסְדוֹם",
          "marked_html": "<span class=\"girsa-letter-sub\">כ</span>סְדוֹם",
          "abbrev": false,
          "proposed_vocalized": false,
          "before_context": "שֶׁלֹּא הָיְתָה",
          "after_context": "דְּאִילּוּ בִּסְדוֹם"
        }
      ]
    }
  ]
}